edouard2023/__init__.py
edouard2023/info.py
edouard2023/version.py
edouard2023/clean/fig6.csv
edouard2023/clean/fig7.csv
edouard2023/clean/fig8.csv
edouard2023/clean/info.json
edouard2023/clean/readme.rst
edouard2023/clean/tab1.csv
edouard2023/clean/tab2.csv
edouard2023/clean/tab3.csv
edouard2023-1.1.0.dist-info/licenses/AUTHORS.rst
edouard2023-1.1.0.dist-info/licenses/LICENSE
edouard2023-1.1.0.dist-info/METADATA
edouard2023-1.1.0.dist-info/WHEEL
edouard2023-1.1.0.dist-info/top_level.txt
edouard2023-1.1.0.dist-info/RECORD
